blarg/__init__.py
blarg/cli.py
blarg/main.py
blarg/mdconfig.py
blarg-0.2.0.dist-info/METADATA
blarg-0.2.0.dist-info/WHEEL
blarg-0.2.0.dist-info/entry_points.txt
blarg-0.2.0.dist-info/top_level.txt
blarg-0.2.0.dist-info/RECORD
